MANIFEST.in
README.md
setup.py
graas_observability_utility.egg-info/PKG-INFO
graas_observability_utility.egg-info/SOURCES.txt
graas_observability_utility.egg-info/dependency_links.txt
graas_observability_utility.egg-info/requires.txt
graas_observability_utility.egg-info/top_level.txt
graas_utilities/__init__.py
graas_utilities/configs.py
graas_utilities/ref_Resolver.py
graas_utilities/validation.py
graas_utilities/Schema/Amazon_Product_Performance_Daily_Report.json
graas_utilities/Schema/Amazon_Sponsored_Brands_Attributed_Purchases_Daily_Report.json
graas_utilities/Schema/Amazon_Sponsored_Brands_Campaign_Daily_Report.json
graas_utilities/Schema/Amazon_Sponsored_Display_Advertised_Product_Daily_Report.json
graas_utilities/Schema/Amazon_Sponsored_Display_Campaign_Daily_Report.json
graas_utilities/Schema/Amazon_Sponsored_Products_Advertised_Product_Daily_Report.json
graas_utilities/Schema/Amazon_Sponsored_Products_Campaign_Daily_Report.json
graas_utilities/Schema/Amazon_Store_Key_Metrics_Daily_Report.json
graas_utilities/Schema/Amazon_Store_Key_Metrics_Hourly_Daily_Report.json
graas_utilities/Schema/Amazon_Traffic_Metrics_Daily_Report.json
graas_utilities/Schema/Flipkart_PLA_Campaign_Seller_Portal_Daily_Report.json
graas_utilities/Schema/Flipkart_PLA_Consolidated_FSN_seller_Portal_Daily_Report.json
graas_utilities/Schema/Flipkart_Search_Traffic_Report_Daily_Report.json
graas_utilities/Schema/Lazada_Customers_Insight_monthly_Report.json
graas_utilities/Schema/Lazada_Keywords_Onsite_daily_Report.json
graas_utilities/Schema/Lazada_Product_Performance_Daily_Report.json
graas_utilities/Schema/Lazada_Product_Sponsored_Affiliate_Report_Daily_monthly_Report.json
graas_utilities/Schema/Lazada_Store_Key_Metrics_monthly_Report.json
graas_utilities/Schema/Lazada_mkp_onsite_campaign_monthly_Report.json
graas_utilities/Schema/Lazada_offsite_campaign_Daily_Report.json
graas_utilities/Schema/Lazada_onsite_campaign_monthly_Report.json
graas_utilities/Schema/Shopee_Keywords_Onsite_daily_Report.json
graas_utilities/Schema/Shopee_Marketing_Add_On_Deal_Key_Metrics_Daily_Report.json
graas_utilities/Schema/Shopee_Marketing_Add_On_Deal_Trends_Daily_Report.json
graas_utilities/Schema/Shopee_Marketing_BundleDeal_Overview_Daily_Report.json
