Metadata-Version: 2.1
Name: graas-observability-utility
Version: 1.6.1
Summary: A small wrapper around data observability
Home-page: https://bitbucket.org/shoptimizeanalytics/graas-observability-utility
Author: Graas
Author-email: priyanka.patel@graas.ai
Keywords: utility
Classifier: Development Status :: 4 - Beta
Classifier: Intended Audience :: Developers
Classifier: Topic :: Internet
Classifier: License :: OSI Approved :: MIT License
Classifier: Programming Language :: Python
Classifier: Programming Language :: Python :: 2
Classifier: Programming Language :: Python :: 2.6
Classifier: Programming Language :: Python :: 2.7
Classifier: Programming Language :: Python :: 3
Classifier: Programming Language :: Python :: 3.3
Classifier: Programming Language :: Python :: 3.4
Classifier: Programming Language :: Python :: 3.8
Requires-Dist: jsonschema
